sports/__init__.py
sports/constants.py
sports/errors.py
sports/scores.py
sports/teams.py
sports.py-2.0.10.dist-info/LICENSE
sports.py-2.0.10.dist-info/METADATA
sports.py-2.0.10.dist-info/WHEEL
sports.py-2.0.10.dist-info/top_level.txt
sports.py-2.0.10.dist-info/RECORD
