Metadata-Version: 2.1
Name: sports.py
Version: 2.0.10
Summary: A simple Python package to gather live sports scores
Home-page: https://github.com/evansloan/sports.py
Author: Evan Sloan
Author-email: evansloan082@gmail.com
License: UNKNOWN
Download-URL: https://github.com/evansloan/sports.py/archive/v2.0.10.tar.gz
Keywords: sports,scores,live scores,hockey,basketball,baseball,football
Platform: UNKNOWN
Classifier: Development Status :: 5 - Production/Stable
Classifier: Intended Audience :: Developers
Classifier: License :: OSI Approved :: MIT License
Classifier: Programming Language :: Python :: 3.5
Classifier: Programming Language :: Python :: 3.6
Requires-Python: >=3
